michaelchen/__init__.py
michaelchen/core.py
michaelchen-0.0.0.dist-info/METADATA
michaelchen-0.0.0.dist-info/WHEEL
michaelchen-0.0.0.dist-info/top_level.txt
michaelchen-0.0.0.dist-info/RECORD
